stealth_crawler-0.9.0.dist-info/licenses/LICENSE
stealthcrawler/__init__.py
stealthcrawler/_version.py
stealthcrawler/cli.py
stealthcrawler/core.py
stealthcrawler/fetchers.py
stealthcrawler/parsers.py
stealthcrawler/progress.py
stealthcrawler/utils.py
stealth_crawler-0.9.0.dist-info/METADATA
stealth_crawler-0.9.0.dist-info/WHEEL
stealth_crawler-0.9.0.dist-info/entry_points.txt
stealth_crawler-0.9.0.dist-info/top_level.txt
stealth_crawler-0.9.0.dist-info/RECORD
