Metadata-Version: 2.4
Name: stealth-crawler
Version: 0.9.0
Summary: A stealth web crawler using headless Chrome
Author-email: Kaden Gruizenga <kjgruiz@pm.me>
License-Expression: GPL-3.0-or-later
Project-URL: Homepage, https://github.com/kgruiz/stealth-crawler
Project-URL: Source, https://github.com/kgruiz/stealth-crawler
Project-URL: Issues, https://github.com/kgruiz/stealth-crawler/issues
Classifier: Development Status :: 4 - Beta
Classifier: Intended Audience :: Developers
Classifier: Programming Language :: Python :: 3
Classifier: Programming Language :: Python :: 3.10
Classifier: Programming Language :: Python :: 3.11
Classifier: Programming Language :: Python :: 3.12
Classifier: Programming Language :: Python :: 3.13
Requires-Python: >=3.10
License-File: LICENSE
Requires-Dist: pydoll-python
Requires-Dist: html2text
Requires-Dist: rich
Requires-Dist: click
Provides-Extra: dev
Requires-Dist: pytest; extra == "dev"
Requires-Dist: pytest-asyncio; extra == "dev"
Requires-Dist: aiohttp; extra == "dev"
Requires-Dist: black; extra == "dev"
Requires-Dist: ruff; extra == "dev"
Requires-Dist: setuptools_scm[toml]>=6.2; extra == "dev"
Requires-Dist: build; extra == "dev"
Requires-Dist: twine; extra == "dev"
Requires-Dist: wheel; extra == "dev"
Dynamic: license-file
